cryptoguard/__init__.py
cryptoguard/cryptoguard.py
cryptoguard/testing_suites/ent
cryptoguard/testing_suites/pr
cryptoguard/testing_suites/testu
cryptoguard/testing_suites/sts-2.1.2/assess
cryptoguard/testing_suites/sts-2.1.2/makefile
cryptoguard/testing_suites/sts-2.1.2/data/BBS.dat
cryptoguard/testing_suites/sts-2.1.2/data/data.bad_rng
cryptoguard/testing_suites/sts-2.1.2/data/data.e
cryptoguard/testing_suites/sts-2.1.2/data/data.pi
cryptoguard/testing_suites/sts-2.1.2/data/data.sha1
cryptoguard/testing_suites/sts-2.1.2/data/data.sqrt2
cryptoguard/testing_suites/sts-2.1.2/data/data.sqrt3
cryptoguard/testing_suites/sts-2.1.2/experiments/create-dir-script
cryptoguard/testing_suites/sts-2.1.2/experiments/AlgorithmTesting/finalAnalysisReport.txt
cryptoguard/testing_suites/sts-2.1.2/experiments/AlgorithmTesting/freq.txt
cryptoguard/testing_suites/sts-2.1.2/experiments/AlgorithmTesting/ApproximateEntropy/results.txt
cryptoguard/testing_suites/sts-2.1.2/experiments/AlgorithmTesting/ApproximateEntropy/stats.txt
cryptoguard/testing_suites/sts-2.1.2/experiments/AlgorithmTesting/BlockFrequency/results.txt
cryptoguard/testing_suites/sts-2.1.2/experiments/AlgorithmTesting/BlockFrequency/stats.txt
cryptoguard/testing_suites/sts-2.1.2/experiments/AlgorithmTesting/CumulativeSums/data1.txt
cryptoguard/testing_suites/sts-2.1.2/experiments/AlgorithmTesting/CumulativeSums/data2.txt
cryptoguard/testing_suites/sts-2.1.2/experiments/AlgorithmTesting/CumulativeSums/results.txt
cryptoguard/testing_suites/sts-2.1.2/experiments/AlgorithmTesting/CumulativeSums/stats.txt
cryptoguard/testing_suites/sts-2.1.2/experiments/AlgorithmTesting/FFT/results.txt
cryptoguard/testing_suites/sts-2.1.2/experiments/AlgorithmTesting/FFT/stats.txt
cryptoguard/testing_suites/sts-2.1.2/experiments/AlgorithmTesting/Frequency/results.txt
cryptoguard/testing_suites/sts-2.1.2/experiments/AlgorithmTesting/Frequency/stats.txt
cryptoguard-1.0.0.dist-info/LICENSE
cryptoguard-1.0.0.dist-info/METADATA
cryptoguard-1.0.0.dist-info/WHEEL
cryptoguard-1.0.0.dist-info/entry_points.txt
cryptoguard-1.0.0.dist-info/top_level.txt
cryptoguard-1.0.0.dist-info/RECORD
