Metadata-Version: 2.1
Name: cryptoguard
Version: 1.0.0
Summary: cryptoguard is a comprehensive Python package enabling seamless execution of diverse random number testing suites, ensuring the statistical integrity and reliability of random number generators for various applications.
Author-email: John Naizer <jnaizer777@gmail.com>
Project-URL: Homepage, https://github.com/jnaizer/cryptoguard
Classifier: Programming Language :: Python :: 3
Classifier: License :: OSI Approved :: MIT License
Classifier: Operating System :: OS Independent
Requires-Python: >=3.8
License-File: LICENSE
Requires-Dist: tqdm
